sr_vulkan_model_waifu2x/__init__.py
sr_vulkan_model_waifu2x/hook-sr_vulkan_model_waifu2x.py
sr_vulkan_model_waifu2x/models/WAIFU2X_ANIME_UP2X.bin
sr_vulkan_model_waifu2x/models/WAIFU2X_ANIME_UP2X.param
sr_vulkan_model_waifu2x/models/WAIFU2X_ANIME_UP2X_DENOISE0X.bin
sr_vulkan_model_waifu2x/models/WAIFU2X_ANIME_UP2X_DENOISE0X.param
sr_vulkan_model_waifu2x/models/WAIFU2X_ANIME_UP2X_DENOISE1X.bin
sr_vulkan_model_waifu2x/models/WAIFU2X_ANIME_UP2X_DENOISE1X.param
sr_vulkan_model_waifu2x/models/WAIFU2X_ANIME_UP2X_DENOISE2X.bin
sr_vulkan_model_waifu2x/models/WAIFU2X_ANIME_UP2X_DENOISE2X.param
sr_vulkan_model_waifu2x/models/WAIFU2X_ANIME_UP2X_DENOISE3X.bin
sr_vulkan_model_waifu2x/models/WAIFU2X_ANIME_UP2X_DENOISE3X.param
sr_vulkan_model_waifu2x/models/WAIFU2X_CUNET_UP1X_DENOISE0X.bin
sr_vulkan_model_waifu2x/models/WAIFU2X_CUNET_UP1X_DENOISE0X.param
sr_vulkan_model_waifu2x/models/WAIFU2X_CUNET_UP1X_DENOISE1X.bin
sr_vulkan_model_waifu2x/models/WAIFU2X_CUNET_UP1X_DENOISE1X.param
sr_vulkan_model_waifu2x/models/WAIFU2X_CUNET_UP1X_DENOISE2X.bin
sr_vulkan_model_waifu2x/models/WAIFU2X_CUNET_UP1X_DENOISE2X.param
sr_vulkan_model_waifu2x/models/WAIFU2X_CUNET_UP1X_DENOISE3X.bin
sr_vulkan_model_waifu2x/models/WAIFU2X_CUNET_UP1X_DENOISE3X.param
sr_vulkan_model_waifu2x/models/WAIFU2X_CUNET_UP2X.bin
sr_vulkan_model_waifu2x/models/WAIFU2X_CUNET_UP2X.param
sr_vulkan_model_waifu2x/models/WAIFU2X_CUNET_UP2X_DENOISE0X.bin
sr_vulkan_model_waifu2x/models/WAIFU2X_CUNET_UP2X_DENOISE0X.param
sr_vulkan_model_waifu2x/models/WAIFU2X_CUNET_UP2X_DENOISE1X.bin
sr_vulkan_model_waifu2x/models/WAIFU2X_CUNET_UP2X_DENOISE1X.param
sr_vulkan_model_waifu2x/models/WAIFU2X_CUNET_UP2X_DENOISE2X.bin
sr_vulkan_model_waifu2x/models/WAIFU2X_CUNET_UP2X_DENOISE2X.param
sr_vulkan_model_waifu2x/models/WAIFU2X_CUNET_UP2X_DENOISE3X.bin
sr_vulkan_model_waifu2x/models/WAIFU2X_CUNET_UP2X_DENOISE3X.param
sr_vulkan_model_waifu2x/models/WAIFU2X_PHOTO_UP2X.bin
sr_vulkan_model_waifu2x/models/WAIFU2X_PHOTO_UP2X.param
sr_vulkan_model_waifu2x-1.0.1.dist-info/METADATA
sr_vulkan_model_waifu2x-1.0.1.dist-info/WHEEL
sr_vulkan_model_waifu2x-1.0.1.dist-info/entry_points.txt
sr_vulkan_model_waifu2x-1.0.1.dist-info/top_level.txt
sr_vulkan_model_waifu2x-1.0.1.dist-info/RECORD
